LICENSE.txt
MANIFEST.in
Makefile
README.rst
cas.py
requirements-dev.txt
requirements.txt
setup.py
nereo_python_cas.egg-info/PKG-INFO
nereo_python_cas.egg-info/SOURCES.txt
nereo_python_cas.egg-info/dependency_links.txt
nereo_python_cas.egg-info/requires.txt
nereo_python_cas.egg-info/top_level.txt