Metadata-Version: 1.1
Name: nereo-python-cas
Version: 1.0.0
Summary: Python CAS client library
Home-page: https://github.com/Nereo/python-cas
Author: Francois Voron
Author-email: francois.voron@nereo.fr
License: MIT
Download-URL: https://github.com/Nereo/python-cas/releases
Keywords: cas,cas2,cas3,client,sso,single sign-on,authentication,auth
Platform: UNKNOWN
Classifier: Development Status :: 5 - Production/Stable
Classifier: Environment :: Web Environment
Classifier: Intended Audience :: Developers
Classifier: License :: OSI Approved :: MIT License
Classifier: Natural Language :: English
Classifier: Operating System :: OS Independent
Classifier: Topic :: Internet :: WWW/HTTP
